openassetio/__init__.py
openassetio/_openassetio.cp310-win_amd64.pyd
openassetio/_windows.py
openassetio/access.py
openassetio/errors.py
openassetio/log.py
openassetio/openassetio-python.dll
openassetio/openassetio-python.lib
openassetio/openassetio-ui.dll
openassetio/openassetio-ui.lib
openassetio/openassetio.dll
openassetio/openassetio.lib
openassetio/py.typed
openassetio/trait.py
openassetio/utils.py
openassetio/_openassetio/__init__.pyi
openassetio/_openassetio/access.pyi
openassetio/_openassetio/constants.pyi
openassetio/_openassetio/errors.pyi
openassetio/_openassetio/hostApi.pyi
openassetio/_openassetio/log.pyi
openassetio/_openassetio/managerApi.pyi
openassetio/_openassetio/pluginSystem.pyi
openassetio/_openassetio/trait.pyi
openassetio/_openassetio/utils.pyi
openassetio/_openassetio/ui/__init__.pyi
openassetio/_openassetio/ui/access.pyi
openassetio/_openassetio/ui/hostApi.pyi
openassetio/_openassetio/ui/managerApi.pyi
openassetio/_openassetio/ui/pluginSystem.pyi
openassetio/hostApi/HostInterface.py
openassetio/hostApi/__init__.py
openassetio/hostApi/terminology.py
openassetio/managerApi/__init__.py
openassetio/pluginSystem/PythonPluginSystem.py
openassetio/pluginSystem/PythonPluginSystemManagerImplementationFactory.py
openassetio/pluginSystem/PythonPluginSystemManagerPlugin.py
openassetio/pluginSystem/PythonPluginSystemPlugin.py
openassetio/pluginSystem/__init__.py
openassetio/test/__init__.py
openassetio/test/manager/__init__.py
openassetio/test/manager/__main__.py
openassetio/test/manager/_implementation.py
openassetio/test/manager/apiComplianceSuite.py
openassetio/test/manager/harness.py
openassetio/ui/__init__.py
openassetio/ui/access.py
openassetio/ui/hostApi/__init__.py
openassetio/ui/managerApi/UIDelegateInterface.py
openassetio/ui/managerApi/__init__.py
openassetio/ui/pluginSystem/PythonPluginSystemUIDelegateImplementationFactory.py
openassetio/ui/pluginSystem/PythonPluginSystemUIDelegatePlugin.py
openassetio/ui/pluginSystem/__init__.py
openassetio-1.0.0.dist-info/METADATA
openassetio-1.0.0.dist-info/WHEEL
openassetio-1.0.0.dist-info/top_level.txt
openassetio-1.0.0.dist-info/RECORD
