Metadata-Version: 2.4
Name: openassetio
Version: 1.0.0
Summary: An open-source interoperability standard for tools and content management systems used in media production.
Author-email: Contributors to the OpenAssetIO project <openassetio-discussion@lists.aswf.io>
Project-URL: Source, https://github.com/OpenAssetIO/OpenAssetIO
Project-URL: Documentation, https://docs.openassetio.org/OpenAssetIO
Project-URL: Issues, https://github.com/OpenAssetIO/OpenAssetIO/issues
Keywords: asset,ams,dam,mam,pipeline,dcc,media,resolver
Classifier: Development Status :: 5 - Production/Stable
Classifier: Intended Audience :: Developers
Classifier: Topic :: Software Development :: Build Tools
Classifier: License :: OSI Approved :: Apache Software License
Classifier: Natural Language :: English
Classifier: Operating System :: MacOS
Classifier: Operating System :: Microsoft :: Windows
Classifier: Operating System :: POSIX :: Linux
Classifier: Programming Language :: Python :: 3
Classifier: Programming Language :: Python :: 3.10
Classifier: Programming Language :: Python :: 3.11
Classifier: Topic :: Software Development :: Libraries :: Python Modules
Classifier: Topic :: Software Development :: Object Brokering
Classifier: Topic :: System :: Distributed Computing
Classifier: Topic :: System :: Filesystems
Requires-Python: >=3.10
